LICENSE
MANIFEST.in
README.md
package.json
setup.py
dash_keyed_file_browser/0b385b9-main-wps-hmr.js
dash_keyed_file_browser/0b385b9-wps-hmr.json
dash_keyed_file_browser/238d51e-main-wps-hmr.js
dash_keyed_file_browser/238d51e-wps-hmr.json
dash_keyed_file_browser/246113f-main-wps-hmr.js
dash_keyed_file_browser/246113f-wps-hmr.json
dash_keyed_file_browser/7149984-main-wps-hmr.js
dash_keyed_file_browser/7149984-wps-hmr.json
dash_keyed_file_browser/KeyedFileBrowser.py
dash_keyed_file_browser/__init__.py
dash_keyed_file_browser/_imports_.py
dash_keyed_file_browser/c66101c-main-wps-hmr.js
dash_keyed_file_browser/c66101c-wps-hmr.json
dash_keyed_file_browser/d4d53c7-main-wps-hmr.js
dash_keyed_file_browser/d4d53c7-wps-hmr.json
dash_keyed_file_browser/dash_keyed_file_browser.min.js
dash_keyed_file_browser/dash_keyed_file_browser.min.js.map
dash_keyed_file_browser/font-awesome.min.css
dash_keyed_file_browser/metadata.json
dash_keyed_file_browser/output.js
dash_keyed_file_browser/package-info.json
dash_keyed_file_browser/react-keyed-file-browser.css
dash_keyed_file_browser.egg-info/PKG-INFO
dash_keyed_file_browser.egg-info/SOURCES.txt
dash_keyed_file_browser.egg-info/dependency_links.txt
dash_keyed_file_browser.egg-info/top_level.txt