Metadata-Version: 1.1
Name: dash-keyed-file-browser
Version: 0.0.2
Summary: Dash Component for react-keyed-file-browser
Home-page: UNKNOWN
Author: Nick DeRobertis <whoopnip@gmail.com>
Author-email: UNKNOWN
License: MIT
Platform: UNKNOWN
Classifier: Framework :: Dash
